QuickHull/__init__.py
QuickHull/hull.cp36-win32.pyd
QuickHull-1.0.0.dist-info/DESCRIPTION.rst
QuickHull-1.0.0.dist-info/METADATA
QuickHull-1.0.0.dist-info/RECORD
QuickHull-1.0.0.dist-info/WHEEL
QuickHull-1.0.0.dist-info/metadata.json
QuickHull-1.0.0.dist-info/top_level.txt
