Metadata-Version: 2.0
Name: QuickHull
Version: 1.0.0
Summary: QuickHull
Home-page: https://github.com/cprogrammer1994/QuickHull
Author: Szabolcs Dombi
Author-email: cprogrammer1994@gmail.com
License: MIT
Platform: win32
Platform: win64
